solidscraper/__init__.py
solidscraper/solidcookies.py
solidscraper/soliddom.py
solidscraper/solidhttp.py
solidscraper-0.7.7.dist-info/METADATA
solidscraper-0.7.7.dist-info/RECORD
solidscraper-0.7.7.dist-info/WHEEL
solidscraper-0.7.7.dist-info/top_level.txt
