Metadata-Version: 2.1
Name: solidscraper
Version: 0.7.7
Summary: This package lets your script scrape web sites. JQuery-Like API.
Home-page: https://github.com/sergioburdisso/solidscraper
Author: Sergio Burdisso
Author-email: sergio.burdisso@gmail.com
License: MIT
Download-URL: https://github.com/sergioburdisso/solidscraper/tarball/v0.7.7
Keywords: scrape,crawler,crawl,scraper
Platform: UNKNOWN
Classifier: Topic :: Internet :: WWW/HTTP
Classifier: Programming Language :: Python :: Implementation :: PyPy
Classifier: Programming Language :: Python
Classifier: Programming Language :: Python :: 2
Classifier: Programming Language :: Python :: 3
Requires-Dist: future
Requires-Dist: beautifulsoup4 (<5,>=4.4.1)
